casefy/__init__.py
casefy/casefy.py
casefy/py.typed
casefy-1.0.0.dist-info/METADATA
casefy-1.0.0.dist-info/WHEEL
casefy-1.0.0.dist-info/licenses/LICENSE
casefy-1.0.0.dist-info/RECORD
