Metadata-Version: 2.3
Name: casefy
Version: 1.0.0
Summary: Utilities for string case conversion.
Project-URL: Homepage, https://github.com/dmlls/python-casefy
Project-URL: Documentation, https://dmlls.github.io/python-casefy/
Project-URL: GitHub Issues, https://github.com/dmlls/python-casefy/issues
Project-URL: GitHub Repo, https://github.com/dmlls/python-casefy/
Author-email: Diego Miguel Lozano <hello@diegomiguel.me>
Maintainer-email: Diego Miguel Lozano <hello@diegomiguel.me>
License: MIT License
Keywords: case,case-converter,casefy,casing
Classifier: Development Status :: 5 - Production/Stable
Classifier: Intended Audience :: Developers
Classifier: License :: OSI Approved :: MIT License
Classifier: Operating System :: OS Independent
Classifier: Programming Language :: Python :: 3
Classifier: Programming Language :: Python :: 3.6
Classifier: Programming Language :: Python :: 3.7
Classifier: Programming Language :: Python :: 3.8
Classifier: Programming Language :: Python :: 3.9
Classifier: Programming Language :: Python :: 3.10
Classifier: Programming Language :: Python :: 3.11
Classifier: Programming Language :: Python :: 3.12
Classifier: Topic :: Text Processing
Classifier: Topic :: Utilities
Requires-Python: >=3.6
